mypackage/__init__.py
mypackage/module.py
tests/__init__.py
tests/test_module.py
mypackage_fenglv-0.1.1.dist-info/LICENSE
mypackage_fenglv-0.1.1.dist-info/METADATA
mypackage_fenglv-0.1.1.dist-info/WHEEL
mypackage_fenglv-0.1.1.dist-info/top_level.txt
mypackage_fenglv-0.1.1.dist-info/RECORD
